{
    "name": "Final Project dataset",
    "pokemon": {
        "count": 3,
        "team": [
            {
                "slot": 1,
                "name": "Dragonite",
                "nickname": "Dalamadur",
                "type": "Dragon",
                "type2": "Flying",
                "moves": ["Draco Meteor", "Hurricane", "Thunder", "Extreme Speed"],
                "item": "Dragoninite",
                "nature": "Calm",
                "EVs": {
                    "HP": 252,
                    "Attack": 0,
                    "Defense": 0,
                    "SpAttack": 252,
                    "SpDefense": 4,
                    "Speed": 0
                }
            },
            {
                "slot": 2,
                "name": "Glaceon",
                "type": "Ice",
                "type2": "",
                "moves": ["Calm Mind", "Ice Beam", "Shadow Ball", "Protect"],
                "item": "Nevermelt Ice",
                "nature": "Modest",
                "EVs": {
                    "HP": 252,
                    "Attack": 0,
                    "Defense": 0,
                    "SpAttack": 252,
                    "SpDefense": 4,
                    "Speed": 0
                }
            },
            {
                "slot": 3,
                "name": "Excadrill",
                "type": "Ground",
                "type2": "Steel",
                "moves": ["Swords Dance", "Earthquake", "Iron Head", "Megahorn"],
                "item": "Excadrite",
                "nature": "Adamant",
                "EVs": {
                    "HP": 252,
                    "Attack": 252,
                    "Defense": 4,
                    "SpAttack": 0,
                    "SpDefense": 0,
                    "Speed": 0
                }
            },
            {
                "slot": 4,
                "name": "",
                "type": "",
                "type2": "",
                "moves": [],
                "item": "",
                "nature": "",
                "EVs": {
                    "HP": 0,
                    "Attack": 0,
                    "Defense": 0,
                    "SpAttack": 0,
                    "SpDefense": 0,
                    "Speed": 0
                }
            },
            {
                "slot": 5,
                "name": "",
                "type": "",
                "type2": "",
                "moves": [],
                "item": "",
                "nature": "",
                "EVs": {
                    "HP": 0,
                    "Attack": 0,
                    "Defense": 0,
                    "SpAttack": 0,
                    "SpDefense": 0,
                    "Speed": 0
                }
            },
            {
                "slot": 6,
                "name": "",
                "type": "",
                "type2": "",
                "moves": [],
                "item": "",
                "nature": "",
                "EVs": {
                    "HP": 0,
                    "Attack": 0,
                    "Defense": 0,
                    "SpAttack": 0,
                    "SpDefense": 0,
                    "Speed": 0
                }
            }
        ]
    }
}